claude_dashboard/__init__.py
claude_dashboard/dashboard.py
claude_dashboard/logging.py
claude_dashboard-0.2.0.dist-info/METADATA
claude_dashboard-0.2.0.dist-info/WHEEL
claude_dashboard-0.2.0.dist-info/entry_points.txt
claude_dashboard-0.2.0.dist-info/licenses/LICENSE
claude_dashboard-0.2.0.dist-info/RECORD
