Metadata-Version: 2.4
Name: claude-dashboard
Version: 0.2.0
Summary: Real-time CLI dashboard for Claude Code tool events
Author: Daniel Ratmiroff
License-Expression: MIT
License-File: LICENSE
Requires-Python: >=3.10
Requires-Dist: python-json-logger>=2.0.0
Requires-Dist: rich>=13.0.0
Provides-Extra: dev
Requires-Dist: pytest>=7.0.0; extra == 'dev'
